Workbook

Sheet Customers
A1: Customer ID | B1: First Name | C1: Last Name | D1: Gender | E1: Date of Birth | F1: City | G1: State | H1: Country | I1: Customer Since | J1: Risk Level
A2: 1 | B2: Rahul | C2: Sharma | D2: Male | E2: 34071 | F2: Kolkata | G2: West Bengal | H2: India | I2: 43539 | J2: Low
A3: 2 | B3: Priya | C3: Mukherjee | D3: Female | E3: 35006 | F3: Kolkata | G3: West Bengal | H3: India | I3: 44022 | J3: Low
A4: 3 | B4: Arjun | C4: Singh | D4: Male | E4: 33498 | F4: Delhi | G4: New Delhi | H4: India | I4: 43122 | J4: Medium
A5: 4 | B5: Neha | C5: Verma | D5: Female | E5: 35850 | F5: Mumbai | G5: Maharashtra | H5: India | I5: 44717 | J5: Low
A6: 5 | B6: Rohan | C6: Das | D6: Male | E6: 33072 | F6: Bangalore | G6: Karnataka | H6: India | I6: 42961 | J6: Medium
A7: 6 | B7: Sneha | C7: Roy | D7: Female | E7: 35559 | F7: Kolkata | G7: West Bengal | H7: India | I7: 44255 | J7: Low
A8: 7 | B8: Amit | C8: Gupta | D8: Male | E8: 33827 | F8: Hyderabad | G8: Telamgana | H8: India | I8: 42692 | J8: High
A9: 8 | B9: Pooja | C9: Nair | D9: Female | E9: 35429 | F9: Chennai | G9: Tamil Nadu | H9: India | I9: 43930 | J9: Low
A10: 9 | B10: Vikram | C10: Patel | D10: Male | E10: 32802 | F10: Ahmedabad | G10: Gujarat | H10: India | I10: 42277 | J10: High
A11: 10 | B11: Ananya | C11: Sen | D11: Female | E11: 36175 | F11: Pune | G11: Maharashtra | H11: India | I11: 44946 | J11: Low
A12: 11 | B12: Karan | C12: Mehta | D12: Male | E12: 34411 | F12: Jaipur | G12: Rajasthan | H12: India | I12: 44326 | J12: Low
A13: 12 | B13: Ritika | C13: Kapoor | D13: Female | E13: 35687 | F13: Chandigarh | G13: Punjab | H13: India | I13: 44791 | J13: Low
... A31: 30 | B31: Ayesha | C31: Khan | D31: Female | E31: 36324 | F31: Bhopal | G31: Madhya Pradesh | H31: India | I31: 44934 | J31: Low

Sheet Accounts
A1: Account Id | B1: Customer Id | C1: Account Number | D1: Account Type | E1: Opening Date | F1: Balance | G1: Status
A2: 1 | B2: 1 | C2: SB100001 | D2: Savings | E2: 43539 | F2: 125000.5 | G2: Active
A3: 2 | B3: 2 | C3: SB100002 | D3: Savings | E3: 44022 | F3: 84500 | G3: Active
A4: 3 | B4: 3 | C4: SA100003 | D4: Salary | E4: 43122 | F4: 156200.75 | G4: Active
A5: 4 | B5: 4 | C5: SB100004 | D5: Savings | E5: 44717 | F5: 35600.25 | G5: Active
A6: 5 | B6: 5 | C6: CU100005 | D6: Current | E6: 42961 | F6: 520000 | G6: Active
A7: 6 | B7: 6 | C7: SB100006 | D7: Savings | E7: 44255 | F7: 45250.5 | G7: Active
A8: 7 | B8: 7 | C8: SA100007 | D8: Salary | E8: 42692 | F8: 985000 | G8: Active
A9: 8 | B9: 8 | C9: SB100008 | D9: Savings | E9: 43930 | F9: 78500 | G9: Active
A10: 9 | B10: 9 | C10: CU100009 | D10: Current | E10: 42277 | F10: 1245000 | G10: Active
A11: 10 | B11: 10 | C11: SB100010 | D11: Savings | E11: 44946 | F11: 18250 | G11: Active
A12: 11 | B12: 11 | C12: SB100011 | D12: Savings | E12: 44326 | F12: 62500 | G12: Active
A13: 12 | B13: 12 | C13: SB100012 | D13: Savings | E13: 44791 | F13: 48900 | G13: Active
... A31: 30 | B31: 30 | C31: SB100030 | D31: Savings | E31: 44934 | F31: 22100 | G31: Active

Sheet Transactions
A1: Transaction Id | B1: Account Id | C1: Transaction Date | D1: Transaction Type | E1: Amount | F1: Merchant Name | G1: Merchant Category | H1: City | I1: State | J1: Payment Mode | K1: Status
A2: 1 | B2: 1 | C2: 46235.386 | D2: Debit | E2: 1250.5 | F2: Amazon | G2: Shopping | H2: Kolkata | I2: West Bengal | J2: UPI | K2: Success
A3: 2 | B3: 2 | C3: 46235.42 | D3: Debit | E3: 450 | F3: Swiggy | G3: Food | H3: Kolkata | I3: West Bengal | J3: UPI | K3: Success
A4: 3 | B4: 3 | C4: 46235.473 | D4: Credit | E4: 65000 | F4: Salary Credit | G4: Salary | H4: Delhi | I4: Delhi | J4: Net Banking | K4: Success
A5: 4 | B5: 4 | C5: 46235.513 | D5: Debit | E5: 3200 | F5: Reliance Digital | G5: Electronics | H5: Mumbai | I5: Maharashtra | J5: Debit Card | K5: Success
A6: 5 | B6: 5 | C6: 46235.57 | D6: Debit | E6: 2100 | F6: Indian Oil | G6: Fuel | H6: Bangalore | I6: Karnataka | J6: Credit Card | K6: Success
A7: 6 | B7: 6 | C7: 46235.599 | D7: Debit | E7: 800 | F7: Zomato | G7: Food | H7: Kolkata | I7: West Bengal | J7: UPI | K7: Success
A8: 7 | B8: 7 | C8: 46235.631 | D8: Credit | E8: 150000 | F8: Client Payment | G8: Business | H8: Hyderabad | I8: Telangana | J8: NEFT | K8: Success
A9: 8 | B9: 8 | C9: 46235.675 | D9: Debit | E9: 560 | F9: Big Bazaar | G9: Groceries | H9: Chennai | I9: Tamil Nadu | J9: Debit Card | K9: Success
A10: 9 | B10: 9 | C10: 46235.747 | D10: Debit | E10: 12000 | F10: MakeMyTrip | G10: Travel | H10: Ahmedabad | I10: Gujarat | J10: Credit Card | K10: Success
A11: 10 | B11: 10 | C11: 46235.766 | D11: Debit | E11: 1500 | F11: Apollo Pharmacy | G11: Healthcare | H11: Pune | I11: Maharashtra | J11: UPI | K11: Success
A12: 11 | B12: 11 | C12: 46236.382 | D12: Debit | E12: 999 | F12: Netflix | G12: Entertainment | H12: Jaipur | I12: Rajasthan | J12: Credit Card | K12: Success
A13: 12 | B13: 12 | C13: 46236.407 | D13: Debit | E13: 1800 | F13: Myntra | G13: Shopping | H13: Chandigarh | I13: Punjab | J13: UPI | K13: Success
... A46: 45 | B46: 3 | C46: 46238.699 | D46: Debit | E46: 172000 | F46: Unknown Electronics | G46: Electronics | H46: Bangalore | I46: Karnataka | J46: Debit Card | K46: Success

Sheet Fraud Risk Transactions
A1: Transaction ID | B1: Account ID | C1: Customer ID | D1: Transaction Date | E1: Transaction Type | F1: Amount | G1: Merchant Name | H1: Merchant Category | I1: City | J1: State | K1: Payment Mode | L1: Status | M1: Customer Risk Level | N1: Fraud Flag | O1: Fraud Risk Reason
A2: 1 | B2: 1 | C2: 1 | D2: 46235.386 | E2: Debit | F2: 1250.5 | G2: Amazon | H2: Shopping | I2: Kolkata | J2: West Bengal | K2: UPI | L2: Success | M2: {=XLOOKUP(C2,Customers!A:A,Customers!J:J)} -> Low | N2: =IF(OR(F2>50000,L2="Failed",M2="High"),"Review","Normal") -> Normal | O2: =IF(AND(F2>50000,L2="Failed",M2="High"),"High Value + Failed + High Risk",IF(F2>50000,"High Value Transaction",IF(L2="Failed","Failed Transaction",IF(M2="High","High Risk Customer","Normal")))) -> Normal
A3: 2 | B3: 2 | C3: 2 | D3: 46235.42 | E3: Debit | F3: 450 | G3: Swiggy | H3: Food | I3: Kolkata | J3: West Bengal | K3: UPI | L3: Success | M3: {=XLOOKUP(C3,Customers!A:A,Customers!J:J)} -> Low | N3: =IF(OR(F3>50000,L3="Failed",M3="High"),"Review","Normal") -> Normal | O3: =IF(AND(F3>50000,L3="Failed",M3="High"),"High Value + Failed + High Risk",IF(F3>50000,"High Value Transaction",IF(L3="Failed","Failed Transaction",IF(M3="High","High Risk Customer","Normal")))) -> Normal
A4: 3 | B4: 3 | C4: 3 | D4: 46235.473 | E4: Credit | F4: 65000 | G4: Salary Credit | H4: Salary | I4: Delhi | J4: Delhi | K4: Net Banking | L4: Success | M4: {=XLOOKUP(C4,Customers!A:A,Customers!J:J)} -> Medium | N4: =IF(OR(F4>50000,L4="Failed",M4="High"),"Review","Normal") -> Review | O4: =IF(AND(F4>50000,L4="Failed",M4="High"),"High Value + Failed + High Risk",IF(F4>50000,"High Value Transaction",IF(L4="Failed","Failed Transaction",IF(M4="High","High Risk Customer","Normal")))) -> High Value Transaction
A5: 4 | B5: 4 | C5: 4 | D5: 46235.513 | E5: Debit | F5: 3200 | G5: Reliance Digital | H5: Electronics | I5: Mumbai | J5: Maharashtra | K5: Debit Card | L5: Success | M5: {=XLOOKUP(C5,Customers!A:A,Customers!J:J)} -> Low | N5: =IF(OR(F5>50000,L5="Failed",M5="High"),"Review","Normal") -> Normal | O5: =IF(AND(F5>50000,L5="Failed",M5="High"),"High Value + Failed + High Risk",IF(F5>50000,"High Value Transaction",IF(L5="Failed","Failed Transaction",IF(M5="High","High Risk Customer","Normal")))) -> Normal
A6: 5 | B6: 5 | C6: 5 | D6: 46235.57 | E6: Debit | F6: 2100 | G6: Indian Oil | H6: Fuel | I6: Bangalore | J6: Karnataka | K6: Credit Card | L6: Success | M6: {=XLOOKUP(C6,Customers!A:A,Customers!J:J)} -> Medium | N6: =IF(OR(F6>50000,L6="Failed",M6="High"),"Review","Normal") -> Normal | O6: =IF(AND(F6>50000,L6="Failed",M6="High"),"High Value + Failed + High Risk",IF(F6>50000,"High Value Transaction",IF(L6="Failed","Failed Transaction",IF(M6="High","High Risk Customer","Normal")))) -> Normal
A7: 6 | B7: 6 | C7: 6 | D7: 46235.599 | E7: Debit | F7: 800 | G7: Zomato | H7: Food | I7: Kolkata | J7: West Bengal | K7: UPI | L7: Success | M7: {=XLOOKUP(C7,Customers!A:A,Customers!J:J)} -> Low | N7: =IF(OR(F7>50000,L7="Failed",M7="High"),"Review","Normal") -> Normal | O7: =IF(AND(F7>50000,L7="Failed",M7="High"),"High Value + Failed + High Risk",IF(F7>50000,"High Value Transaction",IF(L7="Failed","Failed Transaction",IF(M7="High","High Risk Customer","Normal")))) -> Normal
A8: 7 | B8: 7 | C8: 7 | D8: 46235.631 | E8: Credit | F8: 150000 | G8: Client Payment | H8: Business | I8: Hyderabad | J8: Telangana | K8: NEFT | L8: Success | M8: {=XLOOKUP(C8,Customers!A:A,Customers!J:J)} -> High | N8: =IF(OR(F8>50000,L8="Failed",M8="High"),"Review","Normal") -> Review | O8: =IF(AND(F8>50000,L8="Failed",M8="High"),"High Value + Failed + High Risk",IF(F8>50000,"High Value Transaction",IF(L8="Failed","Failed Transaction",IF(M8="High","High Risk Customer","Normal")))) -> High Value Transaction
A9: 8 | B9: 8 | C9: 8 | D9: 46235.675 | E9: Debit | F9: 560 | G9: Big Bazaar | H9: Groceries | I9: Chennai | J9: Tamil Nadu | K9: Debit Card | L9: Success | M9: {=XLOOKUP(C9,Customers!A:A,Customers!J:J)} -> Low | N9: =IF(OR(F9>50000,L9="Failed",M9="High"),"Review","Normal") -> Normal | O9: =IF(AND(F9>50000,L9="Failed",M9="High"),"High Value + Failed + High Risk",IF(F9>50000,"High Value Transaction",IF(L9="Failed","Failed Transaction",IF(M9="High","High Risk Customer","Normal")))) -> Normal
A10: 9 | B10: 9 | C10: 9 | D10: 46235.747 | E10: Debit | F10: 12000 | G10: MakeMyTrip | H10: Travel | I10: Ahmedabad | J10: Gujarat | K10: Credit Card | L10: Success | M10: {=XLOOKUP(C10,Customers!A:A,Customers!J:J)} -> High | N10: =IF(OR(F10>50000,L10="Failed",M10="High"),"Review","Normal") -> Review | O10: =IF(AND(F10>50000,L10="Failed",M10="High"),"High Value + Failed + High Risk",IF(F10>50000,"High Value Transaction",IF(L10="Failed","Failed Transaction",IF(M10="High","High Risk Customer","Normal")))) -> High Risk Customer
A11: 10 | B11: 10 | C11: 10 | D11: 46235.766 | E11: Debit | F11: 1500 | G11: Apollo Pharmacy | H11: Healthcare | I11: Pune | J11: Maharashtra | K11: UPI | L11: Success | M11: {=XLOOKUP(C11,Customers!A:A,Customers!J:J)} -> Low | N11: =IF(OR(F11>50000,L11="Failed",M11="High"),"Review","Normal") -> Normal | O11: =IF(AND(F11>50000,L11="Failed",M11="High"),"High Value + Failed + High Risk",IF(F11>50000,"High Value Transaction",IF(L11="Failed","Failed Transaction",IF(M11="High","High Risk Customer","Normal")))) -> Normal
A12: 11 | B12: 11 | C12: 11 | D12: 46236.382 | E12: Debit | F12: 999 | G12: Netflix | H12: Entertainment | I12: Jaipur | J12: Rajasthan | K12: Credit Card | L12: Success | M12: {=XLOOKUP(C12,Customers!A:A,Customers!J:J)} -> Low | N12: =IF(OR(F12>50000,L12="Failed",M12="High"),"Review","Normal") -> Normal | O12: =IF(AND(F12>50000,L12="Failed",M12="High"),"High Value + Failed + High Risk",IF(F12>50000,"High Value Transaction",IF(L12="Failed","Failed Transaction",IF(M12="High","High Risk Customer","Normal")))) -> Normal
A13: 12 | B13: 12 | C13: 12 | D13: 46236.407 | E13: Debit | F13: 1800 | G13: Myntra | H13: Shopping | I13: Chandigarh | J13: Punjab | K13: UPI | L13: Success | M13: {=XLOOKUP(C13,Customers!A:A,Customers!J:J)} -> Low | N13: =IF(OR(F13>50000,L13="Failed",M13="High"),"Review","Normal") -> Normal | O13: =IF(AND(F13>50000,L13="Failed",M13="High"),"High Value + Failed + High Risk",IF(F13>50000,"High Value Transaction",IF(L13="Failed","Failed Transaction",IF(M13="High","High Risk Customer","Normal")))) -> Normal
... A46: 45 | B46: 3 | C46: 3 | D46: 46238.699 | E46: Debit | F46: 172000 | G46: Unknown Electronics | H46: Electronics | I46: Bangalore | J46: Karnataka | K46: Debit Card | L46: Success | M46: {=XLOOKUP(C46,Customers!A:A,Customers!J:J)} -> Medium | N46: =IF(OR(F46>50000,L46="Failed",M46="High"),"Review","Normal") -> Review | O46: =IF(AND(F46>50000,L46="Failed",M46="High"),"High Value + Failed + High Risk",IF(F46>50000,"High Value Transaction",IF(L46="Failed","Failed Transaction",IF(M46="High","High Risk Customer","Normal")))) -> High Value Transaction

Sheet Analysis
D1: 1. Overall KPIs
C2: Total Customers | D2: Total Accounts | E2: Total Transactions | F2: Total Transaction Value | G2: Average Transaction Amount
C3: =COUNTA(Customers!A2:A1002) -> 30 | D3: =COUNTA(Accounts!A2:A1002) -> 30 | E3: =COUNTA(Transactions!A2:A1002) -> 45 | F3: =SUM(Transactions!E2:E1002) -> 3517567.5 | G3: =AVERAGE(Transactions!E2:E1002) -> 78168.167
B6: 2. Transaction Status
B7: Status | C7: Transactions
B8: Success | C8: =countif(Transactions!K:K,B8) -> 44
B9: Failed | C9: =countif(Transactions!K:K,B9) -> 1
B10: Pending | C10: =countif(Transactions!K:K,B10) -> 0
B18: 3. Transaction Type
B19: Transaction Type | C19: Count
B20: Debit | C20: =COUNTIF(Transactions!D:D,B20) -> 40
B21: Credit | C21: =COUNTIF(Transactions!D:D,B21) -> 5
B29: 4. Payment Mode
B30: Payment Mode | C30: Count
B31: UPI | C31: =COUNTIF(Transactions!J:J,B31) -> 16
B32: Debit Card | C32: =COUNTIF(Transactions!J:J,B32) -> 10
B33: Credit Card | C33: =COUNTIF(Transactions!J:J,B33) -> 12
B34: Net Banking | C34: =COUNTIF(Transactions!J:J,B34) -> 4
B35: NEFT | C35: =COUNTIF(Transactions!J:J,B35) -> 2
B36: RTGS | C36: =COUNTIF(Transactions!J:J,B36) -> 1
B41: 5. Customer Risk
B42: Risk Level | C42: Customers
B43: Low | C43: =COUNTIF(Customers!J:J,B43) -> 17
B44: Medium | C44: =COUNTIF(Customers!J:J,B44) -> 8
B45: High | C45: =COUNTIF(Customers!J:J,B45) -> 5
D54: 6. Fraud Analysis
C55: Transactions for Review | D55: Normal Transactions | E55: High Value Transactions | F55: Failed Transactions | G55: High Risk Customer Transactions | H55: Review Rate
C56: =COUNTIF('Fraud Risk Transactions'!N:N,"Review") -> 24 | D56: =COUNTIF('Fraud Risk Transactions'!N:N,"Normal") -> 21 | E56: =COUNTIF('Fraud Risk Transactions'!F:F,">50000") -> 20 | F56: =COUNTIF('Fraud Risk Transactions'!L:L,"Failed") -> 1 | G56: =COUNTIF('Fraud Risk Transactions'!M:M,"High") -> 8 | H56: =C56/(C56/D56) -> 21
C72: Fraud Indicator | D72: Count
C73: High Value Transactions | D73: =E56 -> 20
C74: Failed Transactions | D74: =F56 -> 1
C75: High Risk Customer Transactions | D75: =G56 -> 8
